deepcs/__init__.py
deepcs/display.py
deepcs/fileutils.py
deepcs/metrics.py
deepcs/rng.py
deepcs/testing.py
deepcs/training.py
deepcs-0.2.10.dist-info/licenses/LICENSE.txt
deepcs-0.2.10.dist-info/METADATA
deepcs-0.2.10.dist-info/WHEEL
deepcs-0.2.10.dist-info/top_level.txt
deepcs-0.2.10.dist-info/RECORD
