Metadata-Version: 2.4
Name: deepcs
Version: 0.2.10
Summary: deepcs provides utilitary functions for the CentraleSupelec deeplearning lab works
Author-email: Jeremy Fix <jeremy.fix@centralesupelec.fr>
Maintainer-email: Jeremy Fix <jeremy.fix@centralesupelec.fr>
License: SPDX-License-Identifier: CECILL-C
Keywords: deep learning,CentraleSupelec
Classifier: Development Status :: 4 - Beta
Classifier: Programming Language :: Python
Requires-Python: >=3.8
License-File: LICENSE.txt
Requires-Dist: torch>=1.5.0
Requires-Dist: torchinfo>=0.0.9
Requires-Dist: torchvision>=0.6
Dynamic: license-file
